odoo/addons/multicompany_configuration/README.rst
odoo/addons/multicompany_configuration/__init__.py
odoo/addons/multicompany_configuration/__manifest__.py
odoo/addons/multicompany_configuration/i18n/es.po
odoo/addons/multicompany_configuration/i18n/it.po
odoo/addons/multicompany_configuration/i18n/multicompany_configuration.pot
odoo/addons/multicompany_configuration/models/__init__.py
odoo/addons/multicompany_configuration/models/multicompany_abstract.py
odoo/addons/multicompany_configuration/models/product_category.py
odoo/addons/multicompany_configuration/models/product_template.py
odoo/addons/multicompany_configuration/models/res_partner.py
odoo/addons/multicompany_configuration/readme/CONTRIBUTORS.rst
odoo/addons/multicompany_configuration/readme/DESCRIPTION.rst
odoo/addons/multicompany_configuration/static/description/icon.png
odoo/addons/multicompany_configuration/static/description/index.html
odoo/addons/multicompany_configuration/static/src/js/multicompany_data_field.js
odoo/addons/multicompany_configuration/static/src/scss/multicompany_data_field.scss
odoo/addons/multicompany_configuration/templates/assets.xml
odoo/addons/multicompany_configuration/views/product_category.xml
odoo/addons/multicompany_configuration/views/product_product.xml
odoo/addons/multicompany_configuration/views/product_template.xml
odoo/addons/multicompany_configuration/views/res_partner.xml
odoo14_addon_multicompany_configuration-14.0.1.0.1.dev8.dist-info/METADATA
odoo14_addon_multicompany_configuration-14.0.1.0.1.dev8.dist-info/WHEEL
odoo14_addon_multicompany_configuration-14.0.1.0.1.dev8.dist-info/top_level.txt
odoo14_addon_multicompany_configuration-14.0.1.0.1.dev8.dist-info/RECORD
